otc_api_ref/__init__.py
otc_api_ref/http_codes.py
otc_api_ref/assets/api-site.css
otc_api_ref/assets/api-site.js
otc_api_ref/assets/combobox.js
otc_api_ref/assets/glyphicons-halflings-regular.ttf
otc_api_ref/assets/glyphicons-halflings-regular.woff
otc_api_ref/tests/__init__.py
otc_api_ref/tests/base.py
otc_api_ref/tests/test_basic_example.py
otc_api_ref/tests/test_os_api_ref.py
otc_api_ref/tests/test_warnings.py
otc_api_ref/tests/examples/basic/conf.py
otc_api_ref/tests/examples/basic/index.rst
otc_api_ref/tests/examples/basic/parameters.yaml
otc_api_ref/tests/examples/basic/status.yaml
otc_api_ref/tests/examples/microversions/conf.py
otc_api_ref/tests/examples/microversions/index.rst
otc_api_ref/tests/examples/microversions/parameters.yaml
otc_api_ref/tests/examples/warnings/conf.py
otc_api_ref/tests/examples/warnings/empty_parameters_file.yaml
otc_api_ref/tests/examples/warnings/index.rst
otc_api_ref/tests/examples/warnings/parameters.yaml
otc_api_ref-0.2.0.dist-info/AUTHORS
otc_api_ref-0.2.0.dist-info/LICENSE
otc_api_ref-0.2.0.dist-info/METADATA
otc_api_ref-0.2.0.dist-info/WHEEL
otc_api_ref-0.2.0.dist-info/pbr.json
otc_api_ref-0.2.0.dist-info/top_level.txt
otc_api_ref-0.2.0.dist-info/RECORD
