Metadata-Version: 2.1
Name: otc-api-ref
Version: 0.2.0
Summary: Sphinx Extensions to support API reference sites in OpenTelekomCloud
Home-page: https://docs.otc.t-systems.com/otc-api-ref/latest/
Author: Open Telekom Cloud
License: UNKNOWN
Platform: UNKNOWN
Classifier: Environment :: OpenStack
Classifier: Intended Audience :: Information Technology
Classifier: Intended Audience :: System Administrators
Classifier: License :: OSI Approved :: Apache Software License
Classifier: Operating System :: POSIX :: Linux
Classifier: Programming Language :: Python
Classifier: Programming Language :: Python :: 3
Classifier: Programming Language :: Python :: 3.6
Classifier: Programming Language :: Python :: 3.7
Classifier: Programming Language :: Python :: 3 :: Only
Classifier: Programming Language :: Python :: Implementation :: CPython
Requires-Python: >=3.6
Requires-Dist: pbr (!=2.1.0,>=2.0.0)
Requires-Dist: PyYAML (>=3.12)
Requires-Dist: sphinx (>=4.0.0)
Requires-Dist: openstackdocstheme (>=2.2.1)
